Metadata-Version: 2.1
Name: pathtreelib
Version: 0.2.1
Summary: A tree-based extension to pathlib
Home-page: https://github.com/MCallagher/pathtreelib
Author: Marco Calandro
Author-email: marco.calandro@mensa.it
License: MIT
Project-URL: Documentation, https://pathtreelib.readthedocs.io/en/stable/
Project-URL: source, https://github.com/MCallagher/pathtreelib
Platform: UNKNOWN
Classifier: Development Status :: 3 - Alpha
Classifier: Topic :: Software Development :: Libraries
Classifier: Topic :: System :: Filesystems
Classifier: Topic :: Scientific/Engineering :: Information Analysis
Classifier: Intended Audience :: Developers
Classifier: Intended Audience :: Science/Research
Classifier: License :: OSI Approved :: MIT License
Classifier: Operating System :: OS Independent
Classifier: Programming Language :: Python :: 3.10
Classifier: Programming Language :: Python :: 3.11
Classifier: Programming Language :: Python :: 3.12
Classifier: Programming Language :: Python :: 3.13
License-File: LICENSE
